{
  "QuestID": 60003,
  "QuestText": {
    "QuestInfo": [
      {
        "Language": "JPN",
        "Name": "\u7834\u6EC5\u306E\u9CE5\u7ADC\uFF1F",
        "Client": "\u90F5\u4FBF\u5C4B\u306E\u30BB\u30F3\u30EA",
        "Description": "\u671F\u5F85\u306E\u65B0\u4F5C\u3001\u30E2\u30F3\u30B9\u30BF\u30FC\u30CF\u30F3\u30BF\u30FC\r\n\u30B9\u30C8\u30FC\u30EA\u30FC\u30BA\uFF12\uFF5E\u7834\u6EC5\u306E\u7FFC\uFF5E\u306B\r\n\u767B\u5834\u3059\u308B\u30AD\u30E5\u30FC\u30C8\u306A\u30A2\u30A4\u30EB\u30FC\u3001\r\n\u30C4\u30AD\u30CE\u6BBF\u306F\u77E5\u3063\u3066\u308B\u304B\u30CB\u30E3\uFF1F\r\n\u5F7C\u5973\u306B\u306A\u308A\u304D\u308B\u30A2\u30A4\u30EB\u30FC\u306E\u91CD\u306D\u7740\r\n\u88C5\u5099\u306B\u5FC5\u8981\u306A\u7D20\u6750\u2026\u3053\u306E\u72E9\u731F\u306E\r\n\u9054\u6210\u3067\u9032\u5448\u3057\u3061\u3083\u3046\u305E\u30CB\u30E3\uFF01",
        "Target": "\u30AF\u30EB\u30EB\u30E4\u30C3\u30AF\uFF11\u982D\u3068\u30AA\u30B5\u30A4\u30BA\u30C1\uFF11\u982D\u3068\r\n\u30C9\u30B9\u30D0\u30AE\u30A3\uFF11\u982D\u306E\u72E9\u731F",
        "Fail": "\u5831\u916C\u91D1\u30BC\u30ED\r\n\u30BF\u30A4\u30E0\u30A2\u30C3\u30D7"
      },
      {
        "Language": "ENG",
        "Name": "Bird Wyverns of Ruin?",
        "Client": "Senri the Mailman",
        "Description": "Do you know the Felyne Tsukino,\r\nwho appears in the mew MONSTER\r\nHUNTER STORIES 2: WINGS OF RUIN?\r\nShe\u0027s so cute! Complete this\r\nquest and I\u0027ll give you materials\r\nto forge layered armor to make\r\nyour Palico look just like her!",
        "Target": "Hunt a Kulu-Ya-Ku, a Great Izuchi,\r\nand a Great Baggi",
        "Fail": "Reward hits 0, or time expires"
      },
      {
        "Language": "FRE",
        "Name": "Wyvernes rapaces de la ruine ?",
        "Client": "Senri le postier",
        "Description": "Tu connais la Felyne Tsukino\r\nde MONSTER HUNTER STORIES 2:\r\nWINGS OF RUIN ? Elle est\r\nadorable ! Finis cette qu\u00EAte\r\net je te filerai de quoi\r\nforger une armure sp\u00E9ciale de\r\nPalico pour lui ressembler !",
        "Target": "Chasser un Kulu-Ya-Ku, un Grand Izuchi,\r\net un Grand Baggi",
        "Fail": "Prime \u00E0 0/Temps expir\u00E9"
      },
      {
        "Language": "ITA",
        "Name": "Wyvern rapaci della rovina?",
        "Client": "Senri il postino",
        "Description": "Hai presente la Felyne Tsukino\r\nche compare nel nuovo MONSTER\r\nHUNTER STORIES 2: WINGS OF\r\nRUIN? \u00C8 tenerissima! Completa\r\nla missione e ti dar\u00F2 materiali\r\nper uno stile armatura che far\u00E0\r\nsomigliare il tuo Felyne a lei!",
        "Target": "Caccia un Kulu-Ya-Ku, un Gran Izuchi\r\ne un Gran Baggi",
        "Fail": "Premio a zero o tempo scaduto"
      },
      {
        "Language": "GER",
        "Name": "Vogelwyvern des Ruins?",
        "Client": "Senri der Postbote",
        "Description": "Kennst du Tsukino, die Felyne\r\naus MONSTER HUNTER STORIES 2:\r\nWINGS OF RUIN? Sie ist so s\u00FC\u00DF!\r\nSchlie\u00DF diese Quest ab, dann\r\ngebe ich dir Materialien f\u00FCr\r\neine Dekorr\u00FCstung, mit der\r\ndein Palico aussieht wie sie!",
        "Target": "Erjage einen Kulu-Ya-Ku, einen Gro\u00DF-\r\nIzuchi und einen Gro\u00DFbaggi.",
        "Fail": "Belohnung auf 0 oder Zeit\r\nl\u00E4uft ab."
      },
      {
        "Language": "SPA",
        "Name": "\u00BFWyverns p\u00E1jaro de la ruina?",
        "Client": "Senri el cartero",
        "Description": "\u00BFConoces a la Felyne Tsukino\r\nde MONSTER HUNTER STORIES 2:\r\nWINGS OF RUIN? \u00A1Es mon\u00EDsima!\r\nSi completas esta misi\u00F3n, te\r\ndar\u00E9 materiales para forjar\r\nuna armadura superpuesta para\r\nque tu Felyne se le parezca.",
        "Target": "Caza un Kulu-Ya-Ku, un Gran Izuchi\r\ny un Gran Baggi",
        "Fail": "La recompensa cae a 0\r\no se acaba el tiempo"
      },
      {
        "Language": "RUS",
        "Name": "\u041F\u0435\u0440\u043D\u0430\u0442\u044B\u0435 \u0432\u0438\u0432\u0435\u0440\u043D\u044B \u0433\u0438\u0431\u0435\u043B\u0438?",
        "Client": "\u041F\u043E\u0447\u0442\u0430\u043B\u044C\u043E\u043D \u0421\u044D\u043D\u0440\u0438",
        "Description": "\u0422\u0435\u0431\u0435 \u0432\u0441\u0442\u0440\u0435\u0447\u0430\u043B\u0430\u0441\u044C \u041A\u043E\u0442\u0442 \u0426\u0443\u043A\u0438\u043D\u043E\r\n\u0438\u0437 \u043D\u043E\u0432\u043E\u0433\u043E MONSTER HUNTER\r\nSTORIES 2: WINGS OF RUIN?\r\n\u041E\u043D\u0430 \u2014 \u043C\u0438\u043B\u0430\u0448\u043A\u0430! \u0412\u044B\u043F\u043E\u043B\u043D\u0438 \u044D\u0442\u043E\r\n\u0437\u0430\u0434\u0430\u043D\u0438\u0435, \u0438 \u044F \u0434\u0430\u043C \u0442\u0435\u0431\u0435 \u043C\u0430\u0442\u0435\u0440\u0438\u0430\u043B\u044B\r\n\u0434\u043B\u044F \u043C\u043D\u043E\u0433\u043E\u0441\u043B\u043E\u0439\u043D\u044B\u0445 \u0434\u043E\u0441\u043F\u0435\u0445\u043E\u0432\r\n\u041F\u0430\u043B\u0438\u043A\u043E \u0432 \u0435\u0435 \u0441\u0442\u0438\u043B\u0435!",
        "Target": "\u0412\u044B\u0441\u043B\u0435\u0434\u0438\u0442\u044C \u041A\u0443\u043B\u0443-\u0419\u0430-\u041A\u0443, \u0411\u043E\u043B\u044C\u0448\u043E\u0433\u043E \u0418\u0434\u0437\u0443\u0442\u0438\r\n\u0438 \u0411\u043E\u043B\u044C\u0448\u043E\u0433\u043E \u0411\u0430\u0433\u0433\u0438",
        "Fail": "\u0421\u0447\u0435\u0442\u0447\u0438\u043A \u043D\u0430\u0433\u0440\u0430\u0434\u044B \u0434\u043E\u0445\u043E\u0434\u0438\u0442 \u0434\u043E 0\r\n\u0438\u043B\u0438 \u0438\u0441\u0442\u0435\u043A\u0430\u0435\u0442 \u0432\u0440\u0435\u043C\u044F"
      },
      {
        "Language": "POL",
        "Name": "Ptasie wiwerny zniszczenia?",
        "Client": "Listonosz Senri",
        "Description": "Znasz felink\u0119 Tsukino z nowej\r\ngry MONSTER HUNTER STORIES 2:\r\nWINGS OF RUIN? Jest przes\u0142odka!\r\nUko\u0144cz to zadanie, a dam Ci\r\nmateria\u0142y do wykucia pancerza\r\nwarstwowego, \u017Ceby tw\u00F3j\r\nkole\u017Ckot wygl\u0105da\u0142 tak jak ona!",
        "Target": "Upoluj Kulu-Ya-Ku, Wielkiego Izuchiego\r\ni Wielkiego Baggiego",
        "Fail": "Nagroda r\u00F3wna 0 lub\r\nkoniec czasu"
      },
      {
        "Language": "POR",
        "Name": "Serp\u00E1ssaros da Ru\u00EDna?",
        "Client": "Senri, o carteiro",
        "Description": "Sabe aquela Felyna, a Tsukino,\r\nque aparece no novo MONSTER\r\nHUNTER STORIES 2: WINGS OF RUIN?\r\nEla \u00E9 t\u00E3o linda! Complete esta\r\nmiss\u00E3o e te darei materiais pra\r\nforjar uma armadura em camadas pra\r\ndeixar seu Amigato igual a ela!",
        "Target": "Cace um Kulu-Ya-Ku, um Grande Izuchi\r\ne um Grande Baggi",
        "Fail": "A recompensa chega a 0\r\nou o tempo expira"
      },
      {
        "Language": "KOR",
        "Name": "\uD30C\uBA78\uC758 \uC870\uB8E1?",
        "Client": "\uC6B0\uCCB4\uBD80 \uC13C\uB9AC",
        "Description": "\uC8FC\uBAA9\uBC1B\uB294 \uC2E0\uC791, MONSTER HUNTER\r\nSTORIES 2: WINGS OF RUIN\uC5D0\r\n\uB4F1\uC7A5\uD558\uB294 \uADC0\uC5EC\uC6B4 \uC544\uC774\uB8E8,\r\n\uCE20\uD0A4\uB178 \uC591\uC744 \uC54C\uACE0 \uC788\uB0E5?\r\n\uADF8\uB140\uB85C \uBCC0\uC2E0\uD560 \uC218 \uC788\uB294 \uC544\uC774\uB8E8\uC6A9\r\n\uB367\uC785\uB294 \uC7A5\uBE44\uC5D0 \uD544\uC694\uD55C \uC18C\uC7AC\uB97C\r\n\uC774\uBC88 \uC0AC\uB0E5\uC5D0 \uC131\uACF5\uD558\uBA74 \uC8FC\uACA0\uB2E4\uB0E5!",
        "Target": "\uCFE0\uB8E8\uB8E8\uC57C\uD06C 1\uB9C8\uB9AC\uC640 \uC624\uC0AC\uC774\uC988\uCE58 1\uB9C8\uB9AC\r\n\uADF8\uB9AC\uACE0 \uB3C4\uC2A4\uBC14\uAE30 1\uB9C8\uB9AC \uC0AC\uB0E5",
        "Fail": "\uBCF4\uC218\uAE08 0\r\n\uC2DC\uAC04 \uCD08\uACFC"
      },
      {
        "Language": "ZHT",
        "Name": "\u7834\u6EC5\u7684\u9CE5\u9F8D\uFF1F",
        "Client": "\u90F5\u5DEE\u5343\u91CC",
        "Description": "\u4F60\u807D\u8AAA\u904E\u6708\u8DEF\u95A3\u4E0B\u55CE\uFF1F\r\n\u6708\u8DEF\u95A3\u4E0B\u662F\u5728\u773E\u4EBA\u671F\u76FC\u7684\u65B0\u4F5C\u2500\u2500\r\n\u300AMONSTER HUNTER STORIES 2: \r\nWINGS OF RUIN\u300B\r\n\u88E1\u9762\u767B\u5834\u7684\u53EF\u611B\u827E\u8DEF\u5594\u3002\u53EA\u8981\u5B8C\u6210\r\n\u9019\u5834\u72E9\u7375\u2026\u2026\u6211\u5C31\u7D66\u4F60\u7279\u6B8A\u7D20\u6750\uFF0C\r\n\u88FD\u4F5C\u53EF\u4EE5\u8B8A\u8EAB\u6210\u5979\u7684\u5916\u89C0\u88DD\u5099\u55B5\uFF01",
        "Target": "\u72E9\u73751\u982D\u6414\u9CE5\u30011\u982D\u942E\u9F2C\u9F8D\u738B\u8207\r\n1\u982D\u7720\u72D7\u9F8D\u738B",
        "Fail": "\u5831\u916C\u91D10\r\n\u6642\u9593\u7D50\u675F"
      },
      {
        "Language": "ZHS",
        "Name": "\u6BC1\u706D\u4E4B\u9E1F\u9F99\uFF1F",
        "Client": "\u4FE1\u4F7F\u884C\u5343\u91CC",
        "Description": "\u4F60\u77E5\u4E0D\u77E5\u9053\u4E07\u4F17\u671F\u5F85\u7684\u65B0\u4F5C\r\n\u300AMONSTER HUNTER STORIES 2:\r\nWINGS OF RUIN\u300B\u4E2D\u767B\u573A\u7684\r\n\u53EF\u7231\u827E\u9732\u732B\uFF0C\u6708\u9732\u9601\u4E0B\u55B5\uFF1F\r\n\u53EA\u8981\u4F60\u5B8C\u6210\u8FD9\u573A\u72E9\u730E\u2026\u2026\r\n\u4FFA\u5C31\u5C06\u53EF\u4EE5\u53D8\u8EAB\u4E3A\u6708\u9732\u7684\r\n\u968F\u4ECE\u5916\u89C2\u88C5\u5907\u7684\u7D20\u6750\u9001\u7ED9\u4F60\u55B5\uFF01",
        "Target": "\u72E9\u730E1\u5934\u6414\u9E1F\u30011\u5934\u9570\u9F2C\u9F99\u738B\u548C1\u5934\u7720\u72D7\u9F99\u738B",
        "Fail": "\u62A5\u916C\u91D1\u989D\u4E3A\u96F6\r\n\u65F6\u95F4\u8017\u5C3D"
      },
      {
        "Language": "ARA",
        "Name": "\u062A\u0646\u0627\u0646\u064A\u0646 \u0645\u062C\u0646\u062D\u0629 \u0634\u0628\u064A\u0647\u0629 \u0628\u0627\u0644\u0637\u064A\u0648\u0631 \u062A\u0646\u0634\u0631 \u0627\u0644\u062E\u0631\u0627\u0628\u061F",
        "Client": "\u0633\u0627\u0639\u064A \u0627\u0644\u0628\u0631\u064A\u062F \u0633\u064A\u0646\u0631\u064A",
        "Description": "\u0623\u062A\u0639\u0631\u0641 \u0627\u0644\u0641\u064A\u0644\u0627\u064A\u0646 \u062A\u0633\u0648\u0643\u064A\u0646\u0648\u060C \u0627\u0644\u062A\u064A\r\n\u062A\u0638\u0647\u0631 \u0641\u064A MONSTER\r\nHUNTER STORIES 2: WINGS OF RUIN?\r\n\u0625\u0646\u0647\u0627 \u0644\u0637\u064A\u0641\u0629 \u062C\u062F\u064B\u0627! \u0623\u0643\u0645\u0644 \u0647\u0630\u0647 \u0627\u0644\u0645\u0647\u0645\u0629\r\n\u0648\u0633\u0623\u0645\u0646\u062D\u0643 \u0645\u0648\u0627\u062F \u0644\u062A\u0634\u0643\u064A\u0644 \u062F\u0631\u0639\r\n\u0645\u062A\u0639\u062F\u062F\u0629 \u0627\u0644\u0645\u0633\u062A\u0648\u064A\u0627\u062A \u0644\u064A\u0635\u0628\u062D \u0628\u0627\u0644\u064A\u0643\u0648\r\n\u062E\u0627\u0635\u062A\u0643 \u0634\u0628\u064A\u0647\u064B\u0627 \u0628\u0647\u0627 \u062A\u0645\u0627\u0645\u064B\u0627!",
        "Target": "\u0635\u064A\u062F \u0643\u0648\u0644\u0648-\u064A\u0627-\u0643\u0648\u060C \u0648\u0625\u064A\u0632\u0648\u062A\u0634\u064A \u0627\u0644\u0639\u0638\u064A\u0645\u060C\r\n\u0648\u0628\u0627\u062C\u064A \u0627\u0644\u0639\u0638\u064A\u0645",
        "Fail": "0 \u0636\u0631\u0628\u0627\u062A \u0627\u0644\u0645\u0643\u0627\u0641\u0623\u0629\u060C \u0623\u0648 \u064A\u0646\u0641\u062F \u0627\u0644\u0648\u0642\u062A"
      }
    ],
    "FallbackLanguage": "ENG",
    "DebugName": "",
    "DebugClient": "",
    "DebugDescription": ""
  },
  "QuestData": {
    "QuestType": 1,
    "QuestLevel": 6,
    "EnemyLevel": 3,
    "Map": 5,
    "BaseTime": 21,
    "TimeVariation": 3,
    "TimeLimit": 50,
    "Carts": 3,
    "QuestConditions": [
      0,
      0
    ],
    "TargetTypes": [
      2,
      0
    ],
    "TargetMonsters": [
      351,
      0
    ],
    "TargetItemIds": [
      67108864,
      67108864
    ],
    "TargetAmounts": [
      1,
      0
    ],
    "Monsters": [
      {
        "Id": 351,
        "SpawnCondition": 1,
        "SpawnParam": 0
      },
      {
        "Id": 2,
        "SpawnCondition": 14,
        "SpawnParam": 10
      },
      {
        "Id": 1366,
        "SpawnCondition": 14,
        "SpawnParam": 10
      },
      {
        "Id": 20,
        "SpawnCondition": 14,
        "SpawnParam": 10
      },
      {
        "Id": 94,
        "SpawnCondition": 15,
        "SpawnParam": 10
      },
      {
        "Id": 514,
        "SpawnCondition": 14,
        "SpawnParam": 10
      },
      {
        "Id": 27,
        "SpawnCondition": 14,
        "SpawnParam": 10
      }
    ],
    "ExtraMonsterCount": 2,
    "SwapExitRide": false,
    "SwapFrequencies": [
      0,
      0
    ],
    "SwapConditions": [
      0,
      0
    ],
    "SwapParams": [
      0,
      0
    ],
    "SwapExitTimes": [
      0,
      0
    ],
    "SwapStopType": 1,
    "SwapStopParam": 0,
    "SwapExecType": 0,
    "Reward": {
      "Zenny": 4680,
      "Points": 100,
      "HRP": 280
    },
    "SupplyTable": 60129,
    "Icons": [
      56,
      999,
      999,
      999,
      999
    ],
    "Tutorial": false,
    "FromNpc": false,
    "ArenaParam": {
      "FenceDefaultActive": false,
      "FenceUptime": 0,
      "FenceInitialDelay": 0,
      "FenceCooldown": 0,
      "Pillars": [
        false,
        false,
        false
      ]
    },
    "AutoMatchHR": 0,
    "BattleBGMType": 0,
    "ClearBGMType": 0
  },
  "EnemyData": {
    "SmallMonsters": {
      "SpawnType": 33,
      "HealthTable": 64,
      "AttackTable": 42,
      "PartTable": 30,
      "OtherTable": 0,
      "MultiTable": 0
    },
    "Monsters": [
      {
        "PathId": 10,
        "SetName": "\u30E1\u30A4\u30F3",
        "SubType": 0,
        "IndividualType": 0,
        "HealthTable": 64,
        "AttackTable": 42,
        "PartTable": 30,
        "OtherTable": 0,
        "StaminaTable": 0,
        "Size": 100,
        "SizeTable": 4,
        "Difficulty": 0,
        "MultiTable": 0
      },
      {
        "PathId": 10,
        "SetName": "9",
        "SubType": 0,
        "IndividualType": 0,
        "HealthTable": 64,
        "AttackTable": 42,
        "PartTable": 30,
        "OtherTable": 0,
        "StaminaTable": 0,
        "Size": 100,
        "SizeTable": 4,
        "Difficulty": 0,
        "MultiTable": 0
      },
      {
        "PathId": 10,
        "SetName": "14",
        "SubType": 0,
        "IndividualType": 0,
        "HealthTable": 64,
        "AttackTable": 42,
        "PartTable": 30,
        "OtherTable": 0,
        "StaminaTable": 0,
        "Size": 100,
        "SizeTable": 4,
        "Difficulty": 0,
        "MultiTable": 0
      },
      {
        "PathId": 0,
        "SetName": "2",
        "SubType": 0,
        "IndividualType": 0,
        "HealthTable": 64,
        "AttackTable": 42,
        "PartTable": 30,
        "OtherTable": 0,
        "StaminaTable": 0,
        "Size": 100,
        "SizeTable": 4,
        "Difficulty": 0,
        "MultiTable": 0
      },
      {
        "PathId": 0,
        "SetName": "1",
        "SubType": 0,
        "IndividualType": 0,
        "HealthTable": 64,
        "AttackTable": 42,
        "PartTable": 30,
        "OtherTable": 0,
        "StaminaTable": 0,
        "Size": 100,
        "SizeTable": 4,
        "Difficulty": 0,
        "MultiTable": 0
      },
      {
        "PathId": 0,
        "SetName": "6",
        "SubType": 0,
        "IndividualType": 0,
        "HealthTable": 64,
        "AttackTable": 42,
        "PartTable": 30,
        "OtherTable": 0,
        "StaminaTable": 0,
        "Size": 100,
        "SizeTable": 10,
        "Difficulty": 0,
        "MultiTable": 0
      },
      {
        "PathId": 0,
        "SetName": "19",
        "SubType": 0,
        "IndividualType": 0,
        "HealthTable": 64,
        "AttackTable": 42,
        "PartTable": 30,
        "OtherTable": 0,
        "StaminaTable": 0,
        "Size": 100,
        "SizeTable": 4,
        "Difficulty": 0,
        "MultiTable": 0
      }
    ]
  },
  "RampageData": null
}